{"Job Title": "java sql software development", "Company": "Pentagon Consultancy Services", "Experience": "3 - 8 years", "Salary": "Not Disclosed", "Location": "Kolkata, Mumbai, Hyderabad/Secunderabad, Pune, Chennai, Bangalore/Bengaluru", "Job Description": "Java_SQL Software Development 3-8 yrs java, sql, . net cognos Bangalore, Chennai, Hyderabad, Pune, Mumbai, Kolkata Pentagon Consultancy Services | HR Consultants | Placement Consultants | Recruitment | job consultants | manpower consultancy | Bangalore, India Java_SQL Software Development Skills : Description : Job Description:Should have experience in Java_SQL software development. The basis of the training will be SQL and Java, but the intern may also be exposed to additional skills including . Net and Cognos. The intern will receive both formal and onthe-job training in Java and SQL software development. On completion the intern will have attained skills in multiple programming disciplines having specialized in Java, . Net, SQL or Cognos or a combination of these. Essential Skills / Experience:- Ability to analyze data and problems. - Excellent organizational skills. - Excellent interpersonal, written and verbal communication skills. - Proactive, self driven individual with technical ability and initiative who can deliver with minimal management and oversight. - Able to remain focused and deliverable-oriented while working independently. - Capable of working under pressure and to tight deadlines, while demonstrating flexibility. - Demonstrate strong performance ethos and personal commitment", "Role": "Pay Roll/Compensation Manager,", "Industry Type": "Recruitment, Staffing,", "Functional Area": "HR, Recruitment, Administration, IR,", "Employment Type": "Full Time, Permanent", "Role Category": "HR/ Recruitment / IR", "UG": "Any Graduate in Any Specialization", "PG": "MBA/PGDM in HR/Industrial Relations", "Doctorate": "None", "Key Skills": ["BPO", "Payroll", "Intern", "Staffing", "Cognos", "professional services", "Verbal communication", "SQL", "business process outsourcing", "Recruitment"]}