{"Job Title": "Five Days Working Computer Operator/ Data Entry Operator - Freshers", "Company": "Zen Global Solution ", "Experience": "0 - 3 years", "Salary": "\u20b9 1,75,000 - 3,25,000 P.A. ", "Location": "Bangalore/Bengaluru", "Job Description": "We are looking for Data entry Operator who can excellently maintain all the data for our company You will be handed with all our companys data and your job will be to maintain the records You will be maintaining data records and doing data collection", "Role": "Stenographer/Data Entry Operator,", "Industry Type": "BPO, Call Centre, ITeS,", "Functional Area": "Executive Assistant, Front Office, Data Entry,", "Employment Type": "Full Time, Permanent", "Role Category": "Other", "UG": "Any Graduate in Any Specialization", "PG": "Any Postgraduate in Any Specialization", "Doctorate": "None", "Key Skills": ["12th pass", "graduate", "data entry", "bpo", "domestic bpo", "computer operating", "chat process", "inbound", "computer operator", "back office", "back office operations", "hr", "full time", "part time", "data entry operation", "fresher", "inbound process", "chat", "email support", "backend", "data entry operator", "email", "ms office"]}