{"Job Title": "International Non-Voice Chat Process Executive", "Company": "GHRS TRAINING LLP  ", "Experience": "0 - 2 years", "Salary": "\u20b9 1,00,000 - 3,00,000 P.A. ", "Location": "Pune", "Job Description": "Undergraduate \u2013 0 to 12-month experienceGraduate \u2013 Fresher / Experience/12th +AboveSalary- 15k to 25k + incentivesExcellent communication, Rotational shiftAccommodation Facility AvailableHR Priyanka-8623032485", "Role": "Associate/Senior Associate -(NonTechnical),", "Industry Type": "BPO, Call Centre, ITeS,", "Functional Area": "ITES, BPO, KPO, LPO, Customer Service, Operations,", "Employment Type": "Full Time, Permanent", "Role Category": "Voice", "UG": "Any Graduate in Any Specialization", "Doctorate": "None", "Key Skills": ["BPO", "International Call Center", "Bpo Non Voice", "International BPO", "Chat Process"]}