{"Job Title": "Opening For Freshers in BPO's!! Excellent comms req.", "Company": "Vaishali Gupta ", "Experience": "0 - 3 years", "Salary": "\u20b9 1,50,000 - 2,75,000 P.A. ", "Location": "Noida, Gurgaon/Gurugram, Delhi / NCR", "Job Description": "Hiring for Blended Process for Freshers and Exp for Noida and Gurgaon Location Sat & Sun off5days workingSalary for 0-6mnths- 15k max6-24months- 18kmaxVaishali@ 8368350597VaishaliConsulting19@gmail.comRequired Candidate profileHiring for Bpo's For gurgaon and noida location Excellents comms req.Salary in b/w 13500-18kSat & sun offVaishali@  8368350597Vaishaliconsulting19@gmail.com", "Role": "Associate/Senior Associate -(NonTechnical),", "Industry Type": "BPO, Call Centre, ITeS,", "Functional Area": "ITES, BPO, KPO, LPO, Customer Service, Operations,", "Employment Type": "Full Time, Permanent", "Role Category": "Voice", "UG": "Any Graduate in Any Specialization", "PG": "Any Postgraduate in Any Specialization", "Doctorate": "None", "Key Skills": ["Blended Process", "BPO", "Communication Skills", "Customer Service", "ccs", "Cce", "US Shift", "Voice Process", "Night Shift", "International BPO", "International Voice Process"]}