{"Job Title": "Software Development Engineer (SDE \u2013 2)", "Company": "OSR Consulting Services", "Experience": "4 - 9 years", "Salary": "Not Disclosed", "Location": "Bangalore/Bengaluru", "Job Description": "Roles and ResponsibilitiesJava, sprintboot, MySql, Redis, AWS, will be preferred.Presently work from home is offeredJob Responsibilities and Duties:Write simple, efficient, and maintainable code.Solid grip on the programming basics like DS and algorithms.Meeting with the software development team to discuss project definitions and goals.Designing system integrations and project workflows.Writing clean, scalable Java code.Designing software database architecture.Developing Java-based user interfaces.Prioritizing and distributing development tasks.Validating the functionality and security of the application.Experience with as many of the following tech: Java, sprint boot, MySQL, Redis, AWS, will be preferred.Experience and interests in IoT, ML and AI, will be an advantage.Using coding standards and best practices to ensure quality.Qualifications and Skills\u2022 Graduation \u2013 BE / Btech \u2022 2 \u2013 6 years - backend engineer, software or JAVA design and architect\u2022 Excellent knowledge of web services.\u2022 Sound knowledge of Java technologies.\u2022 Detailed knowledge of software architecture and user interfaces.\u2022 Experience with software design and application programming.\u2022 Prior experience in start-ups or health-tech will be a plusSalary will not be a constraint for the right candidate..\u2022 B.E / B.tech - recognised University", "Role": "Software Developer,", "Industry Type": "IT-Software, Software Services,", "Functional Area": "IT Software - Application Programming, Maintenance,", "Employment Type": "Full Time, Permanent", "Role Category": "Programming & Design", "UG": "B.Tech/B.E. in Any Specialization", "PG": "Any Postgraduate in Any Specialization", "Doctorate": "Doctorate Not Required", "Key Skills": ["Java", " MySql", " AWS", "web services", " Redis", "Software Development ", " ML ", "Java technologies", "springboot", "IoT"]}