{"Job Title": "Huge Requirement For international voice process sal upto 6L", "Company": "IZEE MANPOWER CONSULTANCY PRIVATE LIMITED ", "Experience": "0 - 5 years", "Salary": "\u20b9 1,50,000 - 6,00,000 P.A. ", "Location": "Bangalore/Bengaluru", "Job Description": "Greeting from Izee manpower immediate opening for international voice supportany ug/grad fresher OR with 0.6 Months international voice exp can applysalary upto 6Lrotational shift rotational offFor more information call Bhuvana@7204011041", "Role": "Associate/Senior Associate -(NonTechnical),", "Industry Type": "BPO, Call Centre, ITeS,", "Functional Area": "ITES, BPO, KPO, LPO, Customer Service, Operations,", "Employment Type": "Full Time, Permanent", "Role Category": "Voice", "UG": "Graduation Not Required", "Doctorate": "None", "Key Skills": ["International Call Center", "International BPO", "International Voice Process"]}