{"Job Title": "Immediate Recruitment  -Work From Home -", "Company": "Desicrew Solutions Pvt Ltd", "Experience": "0 - 5 years", "Salary": "\u20b9 50,000 - 80,000 P.A. ", "Location": "Kumbakonam, Cuddalore, Villupuram/Viluppuram, Erode, mayiladuthurai, Nagapattinam, TN Palayam, Kollumangudi, mayavaram", "Job Description": "SPOT OFFER !!! Domestic BPO process non voice, Any Graduate-Fresher or Experienced, , candidates with Basic computer knowledge, Interested candidates apply immediately Reach us @ 99441 95914 - IndraniRequired Candidate profileCandidates can call & confirm your interview appointment,who are willing to join us immediately, should have good internet connectivity and own laptop/PC", "Role": "Trainee,", "Industry Type": "BPO, Call Centre, ITeS,", "Functional Area": "ITES, BPO, KPO, LPO, Customer Service, Operations,", "Employment Type": "Full Time, Freelance/Homebased", "Role Category": "Other", "UG": "Any Graduate in Any Specialization", "Doctorate": "None", "Key Skills": ["BPO", "Customer Service", "Typing", "Semi Voice", "Non Voice", "KPO", "Data Entry", "Bpo Non Voice", "Backend", "Back Office", "WFH", "Domestic BPO", "ITES", "work from home", "Data Entry Operation"]}