{"Job Title": "i-OS Developer", "Company": "Gurus Info Solutions", "Experience": "2 - 7 years", "Salary": "Not Disclosed", "Location": "Pune", "Job Description": " i-OS Developer     Location :   Pune       Skills :   Objective C, i-os native and cross-platform mobile application development.      Job Description :   Extensive experience with i-os mobile app development.      Experience :   2+ years of experience in i-os app development, senior appdevelopers can also apply.      Employer :   GurusInfoSolutions     ", "Role": "Software Developer,", "Industry Type": "BPO, Call Centre, ITeS,", "Functional Area": "IT Software - Application Programming, Maintenance,", "Employment Type": "Full Time, Permanent", "Role Category": "Programming & Design", "UG": "Any Graduate in Any Specialization", "PG": "Post Graduation Not Required", "Doctorate": "None", "Key Skills": ["Mobile application development"]}