{"Job Title": "Software Developer - ASP/.Net", "Company": "Majestic People Infosystems", "Experience": "2 - 4 years", "Salary": "Not Disclosed", "Location": "Coimbatore", "Job Description": "Desired Candidate Profile  Job Description :- Good knowledge in C#- Must have hands-on knowledge in ASP.NET MVC- Must have worked on projects using AngluarJS or other versions in Angular- Create database using SQL Server preferably MS-SQL- Development of software for US clients- Good communication skills are must- Must have good academic scoresLocation Coimbatore, Tamil Nadu Qualifications :-  2-5 years of C#,MVC,  angularjs development experience-  Experience in SQL Server-  Prior experience building customer-facing sites is strongly preferred ", "Role": "Software Developer,", "Industry Type": "IT-Software, Software Services,", "Functional Area": "IT Software - Application Programming, Maintenance,", "Employment Type": "Full Time, Permanent", "Role Category": "Programming & Design", "UG": "BCA in Computers, B.Tech/B.E. in Any Specialization, B.Sc in Any Specialization", "PG": "Any Postgraduate in Any Specialization", "Doctorate": "Doctorate Not Required", "Key Skills": ["C#", "Angularjs", "Software Development", "MS SQL", ".Net", "SQL Server", "ASP.Net MVC", "ASP", "Angular"]}