{"Job Title": "Software Development Specialist", "Company": "NTT Data", "Experience": "2 - 5 years", "Salary": "Not Disclosed", "Location": "Bangalore/Bengaluru", "Job Description": "      The Spark resource would be essentially writing code in PySpark based on the Payment Policy rules that will be provided to him/her .          The code has to be written preferably using Data frames API or at very most SparkSQL API .         Resource may have to assist with Data pulls in to Cloudera using Sqoop .          All logic would be provided to him/her and I personally would work very closely with them.          Finally the Spark code has to be runnable as a batch process via oozie      ", "Role": "Software Developer,", "Industry Type": "IT-Software, Software Services,", "Functional Area": "IT Software - Application Programming, Maintenance,", "Employment Type": "Full Time, Permanent", "Role Category": "Programming & Design", "UG": "Any Graduate in Any Specialization", "PG": "Post Graduation Not Required", "Doctorate": "None", "Key Skills": ["cloudera", "spark", "oozie", "Manager Technology", "sqoop"]}