{"Job Title": "Software Developer", "Company": "Tapsense Technologies", "Experience": "2 - 4 years", "Salary": "Not Disclosed", "Location": "Pune", "Job Description": "Software Developer     Location  : Pune,   Experience: 2-3 years    ", "Role": "Software Developer,", "Industry Type": "IT-Software, Software Services,", "Functional Area": "IT Software - Application Programming, Maintenance,", "Employment Type": "Full Time, Permanent", "Role Category": "Programming & Design", "UG": "Any Graduate in Any Specialization", "PG": "Post Graduation Not Required", "Doctorate": "None", "Key Skills": ["Software Developer"]}