{"JOB DESCRIPTION": "BE Electronics ,  Diploma or BSc Electronics  Skills Required  Common logic ,  Programming C Language ,  Software design Tools ,  KEIL ,  analog circuit design ,  digital circuits ,  Communication protocols know - how ,  in - depth of different Micro - controllers. Process control field knowledge is preferable.   Job Duties   We work closely with hardware engineers and customers to provide customized hardware/software solutions. We are looking for people who are excited about introducing unique features & reliability into embedded devices for the first time ,  and who love coding to the metal. The candidate will be executing embedded C software code as per varied industrialapplications & projects of the company on timely basis.  He will co - work with other hardware & software team members to make sure the product developed is final for market launch.  Any minor modifications ,  as needed will have to be carried out based on Application & service teams review.   Freshers with creative embedded projects are encouraged to apply. Candidates with raw digital & analog intuition with logic without any formal embedded projects will also be considered.", "ROLE": "Software Developer", "INDUSTRY TYPE": "Industrial Products, Heavy Machinery", "FUNCTIONAL AREA": "IT Software - Embedded, EDA, VLSI, ASIC, Chip Design", "EMPLOYMENT TYPE": "Full Time, Permanen", "ROLE CATEGORY": "Programming & Desig", "EDUCATION": {"UG": "B.Tech/B.E. in Computers", "PG": "M.Tech in Computers"}, "KEY SKILL": ["Embedded C", "Software design", "Communication protocols", "C", "Coding", "Analog", "Process control", "Service", "analog circuit design", "Embedded software"]}