{"JOB DESCRIPTION": "1+ years experience in Android App development, UI, API Integration, Knowledge on SOLID principlesExperience on Android SDK & debugging android applicationsDeep understanding of Design Patterns and API DesignBuilt at least two consumer apps", "ROLE": "Software Developer", "INDUSTRY TYPE": "IT-Software, Software Services", "FUNCTIONAL AREA": "IT Software - Application Programming, Maintenance", "EMPLOYMENT TYPE": "Full Time, Permanen", "ROLE CATEGORY": "Programming & Desig", "EDUCATION": {"UG": "Any Graduate in Any Specialization"}, "KEY SKILL": ["Android"]}