{"JOB DESCRIPTION": "Excellent knowledge in C, C , VC , Win32, MFC, ATL, COM and ActiveXStrong in OOP, Debugging skillsStrong Crash Dump AnalysisExperience in Development Tools include debugging skills.Working closely with SME and Team Lead.Design and develop programming systems making specific determinations about system performance.Responding promptly and professionally to bug reports.Review and repair legacy code.Responsible for analysis of current programs including performance, diagnosis and troubleshooting of problem programs, and designing solutions to problematic programming.Writes, edits, and debugs new computer programs for assigned projects, including necessary records and desired output.Document code consistently throughout the development process by listing a description of the program, special instructions, and any changes made in database tables on procedural, modular and database level.", "ROLE": "Software Developer", "INDUSTRY TYPE": "IT-Software, Software Services", "FUNCTIONAL AREA": "IT Software - Application Programming, Maintenance", "EMPLOYMENT TYPE": "Full Time, Permanen", "ROLE CATEGORY": "Programming & Desig", "EDUCATION": {"UG": "B.Tech/B.E. in Computers", "PG": "M.Tech in Computers"}, "KEY SKILL": ["Win32", "com", "development", "C", "code", "Debugging", "Tools", "Programming", "ActiveX", "MFC", "Subject Matter Expert", "Troubleshooting", "Atl Com", "database"]}