{"JOB DESCRIPTION": "Should have knowledge of Java, Python, Node.Js, React, Redux, Vuejs, Linux, Cloud, MySQL, AI.At least 5 years of experience in Finance Techno.", "ROLE": "Software Developer", "INDUSTRY TYPE": "IT-Software, Software Services", "FUNCTIONAL AREA": "IT Software - Application Programming, Maintenance", "EMPLOYMENT TYPE": "Full Time, Permanen", "ROLE CATEGORY": "Programming & Desig", "EDUCATION": {"UG": "B.Tech/B.E. in Computers", "PG": "MCA in Computers"}, "KEY SKILL": ["Java", "Linux", "MySQL", "Node.Js", "React.Js", "Python"]}