{"JOB DESCRIPTION": " Technical skills     Good exposure to .Net, C#, Unix   Oracle, SQL server, UNIX/Lynux    Microsoft Azure Configuration and Deployments   Scripting ( Unix Shell scripting, Power Shell scripting)    TFS/VSTS, TFS Build definitions/Configuration , Oracle Reports    PL/SQL , automated deployment tools such as, TeamCity, Octopus   Deploy, Azure Devops, Sonarqube          ", "ROLE": "Software Developer", "INDUSTRY TYPE": "IT-Software, Software Services", "FUNCTIONAL AREA": "IT Software - Application Programming, Maintenance", "EMPLOYMENT TYPE": "Full Time, Permanen", "ROLE CATEGORY": "Programming & Desig", "EDUCATION": {"UG": "B.Tech/B.E. in Production/Industrial", "PG": "Post Graduation Not Required"}, "KEY SKILL": ["Oracle SQL", "Powershell", "devops", "PLSQL", "microsoft azure", "Deployment", "Unix shell scripting", "Oracle Reports"]}