{"JOB DESCRIPTION": " Experience\n\n2-4 Years of intensive product/ web application development\n\nRequired Skills\n\nHands on experience of MVC,  Scripting languages (like PHP) and MySQL Queries\nExcellent in DB schema design\nFamiliarity with web technologies and best practices for web design\n\nQualification\n\nExcellent in Programming and problem solving\nBE/ BTech/ MTech/ MCA in Computer Science (Prefer: NITs,  BITs,  IITs)\n\nRole & Responsibilities\n\nDesign & Implementation of core platform components\nPlay an active role in team building\n \n\n", "ROLE": "Software Developer", "INDUSTRY TYPE": "Real Estate, Property", "FUNCTIONAL AREA": "IT Software - Application Programming, Maintenance", "EMPLOYMENT TYPE": "Full Time, Permanen", "ROLE CATEGORY": "Programming & Desig", "EDUCATION": {"UG": "B.Tech/B.E. in Computers", "PG": "Post Graduation Not Required"}, "KEY SKILL": ["schema", "software development", "btech", "computer science", "mysql", "mca", "problem solving", "mvc", "web design", "team building"]}