{"JOB DESCRIPTION": "Roles and Responsibilities  Exp: 2 to 5 yearsJob Location: GurgaonJob description1.Good Knowledge in NodeJS, ExpressJS2.Experience in RDBMS (MySQL) and NoSQL (MongoDB)3..Strong analytical skills and problem solving aptitude4.Knowledge of Async design patterns (Promises, Generators, Observables, Async-await, etc)5.Applicable knowledge of web libraries and frameworks such as Angular/React6.Hands on experience with JavaScript Development on both client and server-side7.Knowledge of version control (SVN, Git)8.Knowledge in Web Services/REST.9.Good communication skills.10.Knowledge of other programming language such as JAVA, would be a plus11. NEST Framework and postGreSQL as compulsory. Interested candidates , please share updated resume on sbagati@kloudrac.com Kind Regards,Simpy bagatiRecruitment Specialist at KloudRac Incwww.kloudrac.com8076292478", "ROLE": "Software Developer", "INDUSTRY TYPE": "IT-Software, Software Services", "FUNCTIONAL AREA": "IT Software - Other", "EMPLOYMENT TYPE": "Full Time, Permanen", "ROLE CATEGORY": "Programming & Desig", "EDUCATION": {"UG": "Any Graduate in Any Specialization"}, "KEY SKILL": ["Mean Stack", "Node", "Node.Js", "MongoDB"]}