{"JOB DESCRIPTION": "***Immediate Opening*** FRESHERS CAN APPLY: Fresher with proven experience and strong technical skills can also apply.IDEAL CANDIDATE WILL HAVE:Minimum Qualification: ME, MTech, BE, B.Tech, MCA, MSc, (Comp. Science).At least 1+ years of software development experience in any of the following technologies  Web Technology stack MERN/LAMP, C# .NET, JAVA,Excellent understanding of OOP concepts.Strong Database skills in any of the following: MS-SQL or MYSQL (Query, Functions, Stored procedures) or MongoDB.Experience with PHP or Node.js, React or Angular.Proven experience with full stack web development is a plus.Experience with troubleshooting and debugging.Good understanding to the Software Development Life Cycle process.Excellent communication, documentation and interpersonal skills, problem solving skills.Proactive, highly motivated attitude and is detailed oriented, quick learner.General understanding Cloud Computing/AWS is plus.Experience with software testing, JIRA bug tracking is a plus.Exciting work environment in fast growing company. Ample opportunity to thrive in your career working on latest technologies along with passionate team of senior developers in India and USA.", "ROLE": "Software Developer", "INDUSTRY TYPE": "IT-Software, Software Services", "FUNCTIONAL AREA": "IT Software - Application Programming, Maintenance", "EMPLOYMENT TYPE": "Full Time, Permanen", "ROLE CATEGORY": "Programming & Desig", "EDUCATION": {"UG": "B.Tech/B.E. in Computers"}, "KEY SKILL": ["C#.Net", "Database", "Web Development", "Java", "Bug Tracking", "Angular", "Software Development", "MS SQL", "MySQL", "PHP", ".Net", "MongoDB", "React.Js"]}