{"JOB DESCRIPTION": "The Senior Software Engineer/ Sr. System Analyst is responsible for planning, processing and executing all technical assignment using ASP .Net in an efficient manner with no assistance from the supervisor. Review and repair legacy code, Analyze, design, coordinate and supervise the development of software systems to form a basis for the solution. Responsible for analysis of current programs including performance, diagnosis and troubleshooting of problem programs, and designing solutions to problematic programming. Making presentations to customer or client audiences or professional peers. Maintain positive client interactions. Responsibilities Must have hands- on experience in the following areas: Off Site Interaction with project stake holders for gathering project requirements and suggesting solutions and implementation. Design & Development of the project which includes, system architecture, Database design, Application Coding, Integration, Implementation and Maintenance. Reviewing the work products like solution documents, code change etc. Provide assistance to testers and support personnel as needed to determine system problems. Identify the requirement from the client. Maintain client databases Strong and effective inter- personal and communication skills and the ability to interact professionally with a diverse group of clients and staff. Provide recommendations to management concerning issues of programmer productivity and software development management. Research and recommend software tools to management. Deliver the project as per the schedule plan. Experience Candidate having 4- 5 years relevant hands- on technical experience preferred experience in working with US based companies. Proficiency in.Net 2.0, 3.0 & 3.5 Frameworks & Web Tools & technologies like ASP.Net, Web Services, XML, AJAX Database knowledge of SQL Server 2008/ 05 Maintain, revise & update existing software. Extensive Knowledge in OOPS concept, WPF, WCF and LINQ. Education Required degree from premier educational institution Required MCA, BCA, M.Tech, B. Tech, B.E. Compensation Excellent compensation and benefits package commensurate with experience. ", "ROLE": "System Analyst", "INDUSTRY TYPE": "Recruitment, Staffing", "FUNCTIONAL AREA": "IT Software - Application Programming, Maintenance", "EMPLOYMENT TYPE": "Full Time, Permanen", "ROLE CATEGORY": "Programming & Desig", "EDUCATION": {"UG": "B.Tech/B.E. in Computers", "PG": "M.Tech in Computers"}, "KEY SKILL": ["bca", "software development", "documents", "xml", "system architecture", "inter", "troubleshooting", "ajax"]}