{"JOB DESCRIPTION": "   Job description      Full stack backend development including overall software development life cycle, starting from specification, coding, testing and maintenance. This is an overseas client project.    Skills :   PHP with Laravel/Lumen frameworks, SQL, latest HTML/CSS, JavaScript/TypeScript, React JS     ", "ROLE": "Software Developer", "INDUSTRY TYPE": "IT-Software, Software Services", "FUNCTIONAL AREA": "IT Software - Application Programming, Maintenance", "EMPLOYMENT TYPE": "Full Time, Permanen", "ROLE CATEGORY": "Programming & Desig", "EDUCATION": {"UG": "Any Graduate in Any Specialization", "PG": "Post Graduation Not Required"}, "KEY SKILL": ["Backend", "CSS", "Coding", "Software development life cycle", "Javascript", "PHP", "HTML", "SQL", "Testing"]}