{"JOB DESCRIPTION": "   Job Description:        l     Develop, test, and deliver enterprise-grade web applications using Java/J2EE and Spring Framework etc.    Gather and clearly document requirements, design and testing results.   Maintain software efficiently through solid knowledge of software lifecycles.   Qualifications:   Bachelor's degree in Computer Science, Statistics, or another quantitative field.   2.    4   +    years of experience as Java developer, with demonstrated ability to effectively develop high-quality software in a collaborative environment.    Previous experience with ERP system development, testing, and implementation.   Proficiency in troubleshooting software issues and debugging a large codebase.   Knowledge of algorithms and data structures.   Familiarity with Linux, Git and Docker is mandatory. ", "ROLE": "Software Developer", "INDUSTRY TYPE": "BPO, Call Centre, ITeS", "FUNCTIONAL AREA": "IT Software - Application Programming, Maintenance", "EMPLOYMENT TYPE": "Full Time, Permanen", "ROLE CATEGORY": "Programming & Desig", "EDUCATION": {"UG": "Any Graduate in Any Specialization", "PG": "Post Graduation Not Required"}, "KEY SKILL": ["Computer science", "GIT", "Linux", "development testing", "HP data protector", "Software Engineer II", "Debugging", "Java Software Engineer", "Data structures", "Recruitment"]}