{"JOB DESCRIPTION": " Job BriefPosition: Software DeveloperExperience Required: 1 to 7 YearsSalary: up to 12 Lakhs per AnnumLocation: Ahmedabad ,Bangalore ,Bharuch ,Bhopal ,Bhubaneswar ,Chandigarh ,Chennai ,Coimbatore ,Delhi ,Gurgaon ,Guwahati ,Hubli ,Hyderabad ,Indore ,Jaipur ,Jamshedpur ,Kanpur ,Kolkata ,Lucknow ,Ludhiana ,Mumbai ,Mysore ,Nagpur ,Noida ,Patna ,Pune ,Rajkot ,Surat ,Vadodara ,Vellore ,Vijayawada ,Visakhapatnam IndiaNotice Period: Immediate to 1 MonthDuties and responsibilities of the jobResearching, designing, implementing, and managing software programsTesting and evaluating new programsIdentifying areas for modification in existing programs and subsequently developing these modificationsWriting and implementing efficient codeDetermining operational practicalityDeveloping quality assurance proceduresDeploying software tools, processes and metricsMaintaining and upgrading existing systemsTraining usersWorking closely with other developers, UX designers, business and systems analystsJob qualifications and requirementsDegrees in the following subjects should be highlighted as particularly advantageous:Computer ScienceComputer Software EngineeringSoftware Programming and DevelopmentEngineeringMathematicsElectronicsPhysicsQualities as Software DeveloperKnowledge and interest in computer systems and the latest technologiesThe ability to learn new technologies quicklyAn analytical mindThe ability to communicate complex procedures to other colleaguesCommercial and business awarenessGood communication skills  both written and verbalSkills (Any):HTML, JavaScript, Jquery, PHP, C#, .NET, Java, Reactjs, React Native, Android, iOS, Magento, MySQL, MS SQL, SQL Server, Laravel, WordPress, Python, Ruby, Go, C, C++, CSS, R, Umreco, ASP.NET, MVC, Web API, .NET Core, Windows Form, WPF, WCF, SOAP UI, NoSQL", "ROLE": "Software Developer", "INDUSTRY TYPE": "IT-Software, Software Services", "FUNCTIONAL AREA": "IT Software - eCommerce, Internet Technologies", "EMPLOYMENT TYPE": "Full Time, Permanen", "ROLE CATEGORY": "Programming & Desig", "EDUCATION": {"UG": "B.Tech/B.E. in Computers, Any Graduate in Any Specialization"}, "KEY SKILL": ["C#", "Angularjs", "Go", "WPF", "Laravel", "Codeigniter", "Core Java", "NoSQL", "MySQL", "SQLite", ".NET", "CakePHP", "Entity Framework", "Ruby", "Python", "Java", "LINQ", "SQL Server", "ASP.Net MVC", "Joomla", "Android", "Django", "Reactjs", "Magento", "Wordpress", "Yii", "MongoDB", "WCF", "React Native"]}