{"JOB DESCRIPTION": "BBTJ1008 -  Software Developer ( Experience 1- 3 years )\n\nPosition: Software Developer\n\nLocation: Chennai,  India\n\nType: Permanent/ Part- time\n\nJob Description\n\nStrong knowledge in CorePHP,  MySql,  OOPS\n\nDesired Skills\n\nStrong knowledge in CorePHP,  MySql,  OOPS\n\nExpertise in at least one from -  Codeigniter /  Laravel /  Slim framework\n\nKnowledge in Angular JS,  Javascript,  Jquery,  HTML,  Ajax/ XML/ JSON\n\nKnowledge in Web Services/ REST/ SOAP/ CURL etc.\n\nAbility to manage multiple products and PHP based projects.\n\nKnowledge in CMS Wordpress,  Drupal would be added advantage.\n\nGood Communication and presentation skills,  should able to handle the pressure\n\nEducation\n\nUG/ PG Any Graduation and specialization\n\nExperience\n\n1- 3 Years", "ROLE": "Software Developer", "INDUSTRY TYPE": "IT-Software, Software Services", "FUNCTIONAL AREA": "IT Software - eCommerce, Internet Technologies", "EMPLOYMENT TYPE": "Full Time, Permanen", "ROLE CATEGORY": "Programming & Desig", "EDUCATION": {"UG": "B.Tech/B.E. in Computers", "PG": "Post Graduation Not Required"}, "KEY SKILL": ["software", "CMS", "HTML", "JSON", "Drupal", "jQuery", "web", "XML", "MySQL", "Wordpress", "PHP", "developer", "Ajax"]}