{"JOB DESCRIPTION": "Software Developer\n\nJob Position: Senior PHP Developer\n\nJob Posted: 01st September,  2018\n\nKnowledge & Skills:\n\nStrong knowledge of PHP. \n\nWeb Frameworks (Laravel,  Codeignitor,  CakePHP) \n\nProject Management Agile Methodology , Waterfall Model \n\nUnderstanding of MVC design patterns \n\nSource Control VSS, SVN \n\nStrong knowledge of front end technologies such as Javascript,  Angular,  HTML5 and CSS3 \n\nResponsibilities\nShould have 1-8 years of experience working with PHP\n\nIntegration of user-facing elements developed by front-end developers.\n\nBuild efficient,  testable and reusable PHP modules\n\nSolve complex performance problems and architectural challenges.\n\nUnderstanding accessibility and security compliance.\n\nKnowledge of MySql database and its declarative query languages", "ROLE": "Software Developer", "INDUSTRY TYPE": "IT-Software, Software Services", "FUNCTIONAL AREA": "IT Software - Application Programming, Maintenance", "EMPLOYMENT TYPE": "Full Time, Permanen", "ROLE CATEGORY": "Programming & Desig", "EDUCATION": {"UG": "Any Graduate in Any Specialization", "PG": "Post Graduation Not Required"}, "KEY SKILL": ["security compliance", "software", "html5", "Project management", "CSS3", "database", "Front end", "MySQL", "design", "Javascript", "PHP", "CakePHP", "Agile methodology", "MVC", "agile"]}